mcptiny/__init__.py
mcptiny/main.py
mcptiny-0.1.0.dist-info/METADATA
mcptiny-0.1.0.dist-info/WHEEL
mcptiny-0.1.0.dist-info/entry_points.txt
mcptiny-0.1.0.dist-info/top_level.txt
mcptiny-0.1.0.dist-info/RECORD
