Metadata-Version: 2.4
Name: mcptiny
Version: 0.1.0
Summary: A tiny MCP server example
Home-page: https://github.com/lvst-gh/mcptiny
Author: Livingstone
Author-email: Livingstone <livingstone.guo@hotmail.com>
License: MIT
Requires-Python: >=3.13
Requires-Dist: fastmcp>=0.1.0
Dynamic: author
Dynamic: home-page
Dynamic: requires-python
